certora_bins/__init__.py
certora_cli/__init__.py
certora_cli/certoraEqCheck.py
certora_cli/certoraMutate.py
certora_cli/certoraRun.py
certora_cli/EVMVerifier/__init__.py
certora_cli/EVMVerifier/certoraBuild.py
certora_cli/EVMVerifier/certoraBuildCacheManager.py
certora_cli/EVMVerifier/certoraBuildDataClasses.py
certora_cli/EVMVerifier/certoraCloudIO.py
certora_cli/EVMVerifier/certoraCollectRunMetadata.py
certora_cli/EVMVerifier/certoraCompilerParameters.py
certora_cli/EVMVerifier/certoraConfigIO.py
certora_cli/EVMVerifier/certoraContext.py
certora_cli/EVMVerifier/certoraContextAttributes.py
certora_cli/EVMVerifier/certoraContextClass.py
certora_cli/EVMVerifier/certoraContextValidator.py
certora_cli/EVMVerifier/certoraContractFuncs.py
certora_cli/EVMVerifier/certoraExtensionInfo.py
certora_cli/EVMVerifier/certoraJobList.py
certora_cli/EVMVerifier/certoraMiniSpecParser.py
certora_cli/EVMVerifier/certoraNodeFilters.py
certora_cli/EVMVerifier/certoraSourceFinders.py
certora_cli/EVMVerifier/certoraType.py
certora_cli/EVMVerifier/certoraVerifyGenerator.py
certora_cli/EVMVerifier/Compiler/CompilerCollector.py
certora_cli/EVMVerifier/Compiler/CompilerCollectorFactory.py
certora_cli/EVMVerifier/Compiler/CompilerCollectorSol.py
certora_cli/EVMVerifier/Compiler/CompilerCollectorSolBased.py
certora_cli/EVMVerifier/Compiler/CompilerCollectorVy.py
certora_cli/EVMVerifier/Compiler/CompilerCollectorYul.py
certora_cli/EVMVerifier/Compiler/__init__.py
certora_cli/EquivalenceCheck/Eq_default.conf
certora_cli/EquivalenceCheck/Eq_mc_no_out_template.spec
certora_cli/EquivalenceCheck/Eq_mc_template.spec
certora_cli/EquivalenceCheck/Eq_sanity.conf
certora_cli/EquivalenceCheck/Eq_template.spec
certora_cli/EquivalenceCheck/__init__.py
certora_cli/EquivalenceCheck/equivCheck.py
certora_cli/EquivalenceCheck/sanity.spec
certora_cli/Mutate/__init__.py
certora_cli/Mutate/mutateApp.py
certora_cli/Mutate/mutateAttributes.py
certora_cli/Mutate/mutateConstants.py
certora_cli/Mutate/mutateUtil.py
certora_cli_alpha_shelly_localAssignmentFinders-20241109.13.42.43775.dist-info/LICENSE
certora_cli_alpha_shelly_localAssignmentFinders-20241109.13.42.43775.dist-info/METADATA
certora_cli_alpha_shelly_localAssignmentFinders-20241109.13.42.43775.dist-info/WHEEL
certora_cli_alpha_shelly_localAssignmentFinders-20241109.13.42.43775.dist-info/entry_points.txt
certora_cli_alpha_shelly_localAssignmentFinders-20241109.13.42.43775.dist-info/top_level.txt
certora_cli_alpha_shelly_localAssignmentFinders-20241109.13.42.43775.dist-info/RECORD
